edf_helium_core/__init__.py
edf_helium_core/__version__.py
edf_helium_core/concept/__init__.py
edf_helium_core/concept/analysis.py
edf_helium_core/concept/case.py
edf_helium_core/concept/collection.py
edf_helium_core/concept/collector.py
edf_helium_core/concept/constant.py
edf_helium_core/concept/disk_usage.py
edf_helium_core/concept/event.py
edf_helium_core/concept/profile.py
edf_helium_core/concept/rule.py
edf_helium_core/concept/target.py
edf_helium_core-2.0.0.dist-info/licenses/LICENSE
edf_helium_core-2.0.0.dist-info/METADATA
edf_helium_core-2.0.0.dist-info/WHEEL
edf_helium_core-2.0.0.dist-info/top_level.txt
edf_helium_core-2.0.0.dist-info/RECORD
