Metadata-Version: 2.4
Name: edf-helium-core
Version: 2.0.0
Summary: EDF Helium Core
Author-email: CERT-EDF <cert@edf.fr>
License-Expression: MIT
Project-URL: Homepage, https://github.com/cert-edf/helium
Project-URL: Repository, https://github.com/cert-edf/helium
Project-URL: Bug Tracker, https://github.com/cert-edf/helium/issues
Keywords: edf,helium,core
Classifier: Development Status :: 5 - Production/Stable
Classifier: Intended Audience :: End Users/Desktop
Classifier: Operating System :: POSIX :: Linux
Classifier: Programming Language :: Python :: 3
Classifier: Programming Language :: Python :: 3 :: Only
Classifier: Topic :: Utilities
Classifier: Topic :: Security
Requires-Python: >=3.12
License-File: LICENSE
Requires-Dist: edf-fusion~=2.0
Requires-Dist: generaptor~=15.1
Dynamic: license-file
